{
  "emitLegacyScripts": false,
  "name": "easy-defense",
  "tree": {
    "$className": "DataModel",
    "ReplicatedStorage": {
      "Source": {
        "$className": "Folder",
        "Features": {
          "$className": "Folder",
          "App": {
            "$className": "Folder",
            "UI": {
              "$className": "Folder",
              "root.story": {
                "$path": "src/features/app/ui/root.story.luau"
              },
              "RootUI": {
                "$path": "src/features/app/ui/RootUI.luau"
              }
            }
          },
          "Crates": {
            "$className": "Folder",
            "Classes": {
              "$className": "Folder",
              "CrateClient": {
                "$path": "src/features/crates/classes/CrateClient.luau"
              }
            },
            "CrateSlice": {
              "$path": "src/features/crates/CrateSlice.luau"
            },
            "Modules": {
              "$className": "Folder",
              "Crates": {
                "$path": "src/features/crates/modules/Crates.luau"
              }
            },
            "UI": {
              "$className": "Folder",
              "CrateRoot": {
                "$path": "src/features/crates/ui/CrateRoot.luau"
              },
              "Screens": {
                "$className": "Folder",
                "CrateBillboards": {
                  "$path": "src/features/crates/ui/screens/CrateBillboards.luau"
                }
              }
            }
          },
          "Inventory": {
            "$className": "Folder",
            "InventoryServiceClient": {
              "$path": "src/features/inventory/InventoryServiceClient.luau"
            },
            "InventoryServiceUtils": {
              "$path": "src/features/inventory/InventoryServiceUtils.luau"
            },
            "InventorySlice": {
              "$path": "src/features/inventory/InventorySlice.luau"
            },
            "UI": {
              "$className": "Folder",
              "Components": {
                "$className": "Folder",
                "InventoryButton": {
                  "$path": "src/features/inventory/ui/components/InventoryButton.luau"
                },
                "ItemButtonStroke": {
                  "$path": "src/features/inventory/ui/components/ItemButtonStroke.luau"
                },
                "ItemIcon": {
                  "$path": "src/features/inventory/ui/components/ItemIcon.luau"
                }
              },
              "Hooks": {
                "$className": "Folder",
                "useItemDragger": {
                  "$path": "src/features/inventory/ui/hooks/useItemDragger.luau"
                }
              },
              "InventoryRoot": {
                "$path": "src/features/inventory/ui/InventoryRoot.luau"
              },
              "Screens": {
                "$className": "Folder",
                "DraggedItem": {
                  "$path": "src/features/inventory/ui/screens/DraggedItem.luau"
                },
                "InventoryHud": {
                  "$path": "src/features/inventory/ui/screens/InventoryHud.luau"
                }
              }
            }
          },
          "Plots": {
            "$className": "Folder",
            "Classes": {
              "$className": "Folder",
              "PlotClient": {
                "$path": "src/features/plots/classes/PlotClient.luau"
              }
            },
            "PlotServiceClient": {
              "$path": "src/features/plots/PlotServiceClient.luau"
            },
            "PlotServiceUtils": {
              "$path": "src/features/plots/PlotServiceUtils.luau"
            },
            "PlotSlice": {
              "$path": "src/features/plots/PlotSlice.luau"
            },
            "PlotTypes": {
              "$path": "src/features/plots/PlotTypes.luau"
            },
            "UI": {
              "$className": "Folder",
              "PlotRoot": {
                "$path": "src/features/plots/ui/PlotRoot.luau"
              },
              "Screens": {
                "$className": "Folder",
                "CrateTimers": {
                  "$path": "src/features/plots/ui/screens/CrateTimers.luau"
                }
              }
            }
          },
          "Towers": {
            "$className": "Folder",
            "Modules": {
              "$className": "Folder",
              "Towers": {
                "$path": "src/features/towers/modules/Towers.luau"
              }
            }
          }
        },
        "Core": {
          "$className": "Folder",
          "Platform": {
            "$className": "Folder",
            "SoundController": {
              "$path": "src/core/platform/SoundController.luau"
            }
          },
          "UI": {
            "$className": "Folder",
            "Abbreviate": {
              "$path": "src/core/ui/Abbreviate.luau"
            },
            "FormatTime": {
              "$path": "src/core/ui/FormatTime.luau"
            },
            "Hooks": {
              "$className": "Folder",
              "serverTimeAtom": {
                "$path": "src/core/ui/hooks/serverTimeAtom.luau"
              },
              "useAbsSize": {
                "$path": "src/core/ui/hooks/useAbsSize.luau"
              },
              "useDataState": {
                "$path": "src/core/ui/hooks/useDataState.luau"
              },
              "useDeviceInput": {
                "$path": "src/core/ui/hooks/useDeviceInput.luau"
              },
              "useServerTime": {
                "$path": "src/core/ui/hooks/useServerTime.luau"
              },
              "useServerTimeBinding": {
                "$path": "src/core/ui/hooks/useServerTimeBinding.luau"
              },
              "useSpring": {
                "$path": "src/core/ui/hooks/useSpring.luau"
              },
              "useTag": {
                "$path": "src/core/ui/hooks/useTag.luau"
              },
              "useTween": {
                "$path": "src/core/ui/hooks/useTween.luau"
              },
              "useViewportSize": {
                "$path": "src/core/ui/hooks/useViewportSize.luau"
              }
            },
            "Primitives": {
              "$className": "Folder",
              "Button": {
                "$path": "src/core/ui/primitives/Button.luau"
              },
              "ImageLabel": {
                "$path": "src/core/ui/primitives/ImageLabel.luau"
              },
              "TextLabel": {
                "$path": "src/core/ui/primitives/TextLabel.luau"
              }
            },
            "Suffixes": {
              "$path": "src/core/ui/Suffixes.luau"
            },
            "UITypes": {
              "$path": "src/core/ui/UITypes.luau"
            }
          }
        },
        "Game": {
          "$className": "Folder",
          "Assets": {
            "$className": "Folder",
            "ImageIds": {
              "$path": "src/game/assets/ImageIds.luau"
            },
            "Sounds": {
              "$path": "src/game/assets/Sounds.luau"
            }
          },
          "Configs": {
            "$path": "src/game/Configs.luau"
          },
          "Items": {
            "$className": "Folder",
            "DataTemplate": {
              "$path": "src/game/items/DataTemplate.luau"
            },
            "Tiers": {
              "$path": "src/game/items/Tiers.luau"
            }
          }
        },
        "StartUp": {
          "$className": "Folder",
          "MountUI": {
            "$path": "src/startup/MountUI.luau"
          },
          "Client": {
            "$path": "src/startup/Client.client.luau"
          }
        }
      },
      "Packages": {
        "$path": "Packages"
      }
    },
    "ServerScriptService": {
      "Features": {
        "$className": "Folder",
        "Inventory": {
          "$className": "Folder",
          "InventoryServiceServer": {
            "$path": "src/features/inventory/InventoryServiceServer.luau"
          }
        },
        "Plots": {
          "$className": "Folder",
          "Classes": {
            "$className": "Folder",
            "PlotServer": {
              "$path": "src/features/plots/classes/PlotServer.luau"
            }
          },
          "PlotServiceServer": {
            "$path": "src/features/plots/PlotServiceServer.luau"
          }
        }
      },
      "Core": {
        "$className": "Folder"
      },
      "Game": {
        "$className": "Folder"
      },
      "StartUp": {
        "$className": "Folder",
        "Server": {
          "$path": "src/startup/Server.server.luau"
        }
      }
    }
  }
}